Metadata-Version: 2.1
Name: betterbeeswarm
Version: 0.1.0
Summary: Custom implementation of seaborn Beeswarm class
Home-page: https://github.com/tvarovski/BetterBeeswarm
Author: tvarovski (Jerzy Twarowski)
Author-email: tvarovski1@gmail.com
Classifier: Programming Language :: Python :: 3
Classifier: License :: OSI Approved :: MIT License
Classifier: Operating System :: OS Independent
License-File: LICENSE
